ol_openedx_lti_utilities/__init__.py
ol_openedx_lti_utilities/app.py
ol_openedx_lti_utilities/urls.py
ol_openedx_lti_utilities/views.py
ol_openedx_lti_utilities-0.1.2.dist-info/METADATA
ol_openedx_lti_utilities-0.1.2.dist-info/WHEEL
ol_openedx_lti_utilities-0.1.2.dist-info/entry_points.txt
ol_openedx_lti_utilities-0.1.2.dist-info/licenses/LICENSE.txt
ol_openedx_lti_utilities-0.1.2.dist-info/RECORD
