Metadata-Version: 2.4
Name: ol-openedx-lti-utilities
Version: 0.1.2
Summary: An Open edX plugin to add utilities for LTI operations
Author: MIT Office of Digital Learning
License-Expression: BSD-3-Clause
License-File: LICENSE.txt
Requires-Python: >=3.11
Requires-Dist: django>=4.0
Requires-Dist: djangorestframework>=3.14.0
Requires-Dist: edx-django-utils>4.0.0
Requires-Dist: edx-drf-extensions>=10.0.0
Requires-Dist: edx-opaque-keys
